setup.py
src/jlddk/BeautifulSoup.py
src/jlddk/__init__.py
src/jlddk/do_checks.py
src/jlddk/do_setup.py
src/jlddk/script_arun.py
src/jlddk/script_bolus.py
src/jlddk/script_cat.py
src/jlddk/script_clock.py
src/jlddk/script_comp.py
src/jlddk/script_debouncer.py
src/jlddk/script_dirzip.py
src/jlddk/script_fcomp.py
src/jlddk/script_fetcher.py
src/jlddk/script_filelist.py
src/jlddk/script_filter.py
src/jlddk/script_inotify.py
src/jlddk/script_jsoncat.py
src/jlddk/script_ostr.py
src/jlddk/script_pclean.py
src/jlddk/script_run.py
src/jlddk/script_splitter.py
src/jlddk/script_statsubdirs.py
src/jlddk/script_strpkg.py
src/jlddk/script_taskctl.py
src/jlddk/script_touch.py
src/jlddk/script_uncat.py
src/jlddk/script_webdl.py
src/jlddk/script_webscraper.py
src/jlddk/tools_flow.py
src/jlddk/tools_func.py
src/jlddk/tools_logging.py
src/jlddk/tools_misc.py
src/jlddk/tools_os.py
src/jlddk/tools_sys.py
src/jlddk/tools_web.py
src/jlddk.egg-info/PKG-INFO
src/jlddk.egg-info/SOURCES.txt
src/jlddk.egg-info/dependency_links.txt
src/jlddk.egg-info/not-zip-safe
src/jlddk.egg-info/requires.txt
src/jlddk.egg-info/top_level.txt
src/jlddk/agents/__init__.py
src/jlddk/agents/exc.py
src/jlddk/agents/test.py
src/jlddk/agents/test2.py
src/jlddk/block/__init__.py
src/jlddk/block/mq_s3pub.py
src/jlddk/utils/__init__.py
src/jlddk/utils/debug.py
src/scripts/jldarun
src/scripts/jldbolus
src/scripts/jldcat
src/scripts/jldclock
src/scripts/jldcomp
src/scripts/jlddebouncer
src/scripts/jlddirzip
src/scripts/jldfcomp
src/scripts/jldfetcher
src/scripts/jldfilelist
src/scripts/jldfilter
src/scripts/jldinotify
src/scripts/jldjsoncat
src/scripts/jldostr
src/scripts/jldpclean
src/scripts/jldrun
src/scripts/jldsplitter
src/scripts/jldstatsubdirs
src/scripts/jldtaskctl
src/scripts/jldtouch
src/scripts/jlduncat
src/scripts/jldwebdl
src/scripts/jldwebscraper