Metadata-Version: 1.0
Name: jlddk
Version: 0.7.36
Summary: Collection of robots
Home-page: http://www.systemical.com/doc/opensource/jlddk
Author: Jean-Lou Dupont
Author-email: jl@jldupont.com
License: UNKNOWN
Platform: UNKNOWN
